qudit_visualizer/__init__.py
qudit_visualizer/__main__.py
qudit_visualizer/app.py
qudit_visualizer/models.py
qudit_visualizer/wigner.py
qudit_visualizer/static/favicon.ico
qudit_visualizer/static/index.html
qudit_visualizer/static/assets/index-BCfY42IU.js
qudit_visualizer/static/assets/index-DauC1V2D.css
qudit_visualizer-0.1.2.dist-info/METADATA
qudit_visualizer-0.1.2.dist-info/WHEEL
qudit_visualizer-0.1.2.dist-info/entry_points.txt
qudit_visualizer-0.1.2.dist-info/top_level.txt
qudit_visualizer-0.1.2.dist-info/RECORD
