Metadata-Version: 2.4
Name: qudit-visualizer
Version: 0.1.2
Summary: Discrete Wigner-function visualizer for a single qudit of arbitrary dimension d.
Author: Carlo Cepollaro
License: MIT
Project-URL: Homepage, https://github.com/lordrlo/qudit-visualizer
Requires-Python: <3.14,>=3.10
Requires-Dist: fastapi>=0.123.5
Requires-Dist: uvicorn[standard]>=0.38.0
Requires-Dist: dynamiqs>=0.3.3
Requires-Dist: jax>=0.6.2
